gtgt/__init__.py
gtgt/__main__.py
gtgt/bed.py
gtgt/cli.py
gtgt/exonviz.py
gtgt/flask.py
gtgt/models.py
gtgt/mutalyzer.py
gtgt/provider.py
gtgt/range.py
gtgt/transcript.py
gtgt/typed.py
gtgt/ucsc.py
gtgt/variant_validator.py
gtgt/templates/analysis.html.j2
gtgt/templates/documentation.html
gtgt/templates/external.html.j2
gtgt/templates/head.html.j2
gtgt/templates/index.html.j2
gtgt/templates/nav.html
gtgt/templates/results.html.j2
gtgt-0.2.10.dist-info/licenses/LICENSE
gtgt-0.2.10.dist-info/METADATA
gtgt-0.2.10.dist-info/WHEEL
gtgt-0.2.10.dist-info/entry_points.txt
gtgt-0.2.10.dist-info/top_level.txt
gtgt-0.2.10.dist-info/RECORD
