Metadata-Version: 2.4
Name: gtgt
Version: 0.2.10
Summary: Genetic Therapy Generator Toolkit
Home-page: https://github.com/DCRT-LUMC/GTGT
Author: Redmar van den Berg
Author-email: RedmarvandenBerg@lumc.nl
License: AGPL-3.0
Project-URL: Changelog, https://github.com/DCRT-LUMC/GTGT/blob/main/CHANGELOG.rst
Project-URL: Issue Tracker, https://github.com/DCRT-LUMC/GTGT/issues
Classifier: Development Status :: 3 - Alpha
Classifier: Intended Audience :: Developers
Classifier: License :: OSI Approved :: BSD License
Classifier: Operating System :: Unix
Classifier: Programming Language :: Python
Classifier: Programming Language :: Python :: 3
Classifier: Programming Language :: Python :: 3.10
Classifier: Programming Language :: Python :: 3.11
Classifier: Programming Language :: Python :: 3.12
Classifier: Programming Language :: Python :: 3.13
Classifier: Programming Language :: Python :: 3.14
Classifier: Topic :: Utilities
Requires-Python: >=3.10
License-File: LICENSE
Requires-Dist: pydantic
Requires-Dist: setuptools
Requires-Dist: mutalyzer>=3.1.1
Requires-Dist: mutalyzer_hgvs_parser
Requires-Dist: lark==1.2.2
Requires-Dist: exonviz>=0.2.16
Provides-Extra: webserver
Requires-Dist: flask; extra == "webserver"
Dynamic: author
Dynamic: author-email
Dynamic: classifier
Dynamic: description
Dynamic: description-content-type
Dynamic: home-page
Dynamic: license
Dynamic: license-file
Dynamic: project-url
Dynamic: provides-extra
Dynamic: requires-dist
Dynamic: requires-python
Dynamic: summary
